sfdmap2/sfdmap.py
sfdmap2-0.2.2.post2.dist-info/METADATA
sfdmap2-0.2.2.post2.dist-info/WHEEL
sfdmap2-0.2.2.post2.dist-info/RECORD
