Metadata-Version: 2.1
Name: sfdmap2
Version: 0.2.2.post2
Summary: Get E(B-V) values from SFD dust map data
Home-page: https://github.com/simeonreusch/sfdmap2
License: MIT
Author: Kyle Barbary
Maintainer: Simeon Reusch
Maintainer-email: simeon.reusch@desy.de
Requires-Python: >=3.9,<4.0
Classifier: License :: OSI Approved :: MIT License
Classifier: Programming Language :: Python :: 3
Classifier: Programming Language :: Python :: 3.9
Classifier: Programming Language :: Python :: 3.10
Classifier: Programming Language :: Python :: 3.11
Classifier: Programming Language :: Python :: 3.12
Provides-Extra: fits
Requires-Dist: astropy (>=5)
Requires-Dist: fitsio (>=1,<2) ; extra == "fits"
Requires-Dist: numpy (>=1.24.2,<2.0.0)
Project-URL: Repository, https://github.com/simeonreusch/sfdmap2
